greetings_snow/__init__.py
greetings_snow/greetings.py
snow_greeting-0.1.2.dist-info/LICENSE
snow_greeting-0.1.2.dist-info/METADATA
snow_greeting-0.1.2.dist-info/WHEEL
snow_greeting-0.1.2.dist-info/top_level.txt
snow_greeting-0.1.2.dist-info/RECORD
