Metadata-Version: 2.1
Name: snow-greeting
Version: 0.1.2
Summary: A package that prints a snowy greeting message.
Home-page: https://github.com/oracle1993/greetings_snow
Author: oracle1993
Author-email: dragonknight.work.1993@gmail.com
Classifier: Programming Language :: Python :: 3
Classifier: License :: OSI Approved :: MIT License
Classifier: Operating System :: OS Independent
Requires-Python: >=3.6
License-File: LICENSE
